{"id":70624,"name":"24M TECHNOLOGIES","slug":"24m-technologies","state":"MA","country":"United States of America","description":"Battery manufacturer","totalSpending":10000,"filings":2,"yearlySpending":[{"year":2025,"income":10000}],"issues":[{"code":"DEF","display":"Defense"},{"code":"AER","display":"Aerospace"},{"code":"MAN","display":"Manufacturing"},{"code":"ENG","display":"Energy/Nuclear"}],"firms":["STRATEGIC MARKETING INNOVATIONS"],"lobbyists":["PATRICK DAVIS"],"govEntities":["Defense, Dept of (DOD)","Energy, Dept of","HOUSE OF REPRESENTATIVES","SENATE"],"sampleDescriptions":["Battery manufacturing","Battery manufacturing","Battery manufacturing","Funding for the further development of their advanced lithium battery components, electrodes, and cell manufacturing for the Department of Defense and dual-use applications for the Department of Energ","Funding for the further development of their advanced lithium battery components, electrodes, and cell manufacturing for the Department of Defense and dual-use applications for the Department of Energ"]}