{"id":158320,"name":"ASCENDA BIOSCIENCES LLC (FORMERLY DRG LABORATORY LLC)","slug":"ascenda-biosciences-llc-formerly-drg-laboratory-llc","state":"GA","country":"United States of America","description":"Developer and provider of state of the art DNA-based laboratory diagnostic testing","totalSpending":0,"filings":4,"yearlySpending":[{"year":2018,"income":0}],"issues":[{"code":"SCI","display":"Science/Technology"}],"firms":["THE CHARLES GROUP, LLC"],"lobbyists":["PARKER ERICKSON"],"govEntities":["HOUSE OF REPRESENTATIVES"],"sampleDescriptions":["advocating for legislation to protect small clinical labs"]}