{"id":64975,"name":"ATS GROUP DOOEL SKOPJE","slug":"ats-group-dooel-skopje","state":null,"country":"North Macedonia","description":"Manufacturing","totalSpending":680000,"filings":5,"yearlySpending":[{"year":2025,"income":680000}],"issues":[{"code":"MAN","display":"Manufacturing"}],"firms":["VALCOUR LLC"],"lobbyists":["MATTHEW MOWERS","BLAKE CENTER","WILLIAM KILLION"],"govEntities":["U.S. Trade Representative (USTR)"],"sampleDescriptions":["US Manufacturing","US investment","US investment","US investment","US investment"]}