{"id":199570,"name":"BOWLING PROPRIETORS' ASSOCIATION OF AMERICA","slug":"bowling-proprietors-association-of-america","state":"TX","country":"United States of America","description":"Association of Bowling Proprietors and owners","totalSpending":1370000,"filings":35,"yearlySpending":[{"year":2018,"income":120000},{"year":2019,"income":200000},{"year":2020,"income":160000},{"year":2021,"income":220000},{"year":2022,"income":80000},{"year":2023,"income":170000},{"year":2024,"income":200000},{"year":2025,"income":220000}],"issues":[{"code":"SMB","display":"Small Business"},{"code":"ART","display":"Arts/Entertainment"},{"code":"SPO","display":"Sports/Athletics"},{"code":"LBR","display":"Labor Issues/Antitrust/Workplace"}],"firms":["MICHAEL BEST STRATEGIES LLC"],"lobbyists":["SARAH HELTON","THOMAS SCHREIBEL","JEFFRY NICHOLS","HARRISON COLLINS","EMILY GREEN","LEWIS POLAY","BRANDON PALUMBO","BRETT EWER","RYAN LOSAK"],"govEntities":["Small Business Administration (SBA)","HOUSE OF REPRESENTATIVES","SENATE","White House Office","Office of Management & Budget (OMB)"],"sampleDescriptions":["SBA loan programs","SBA loan programs","Music Modernization Act (HR 1551)and issues relating to DOJ consent decrees","sports betting","SBA loan programs"]}