{"id":212911,"name":"BRIDGE STREET GROUP LLC ON BEHALF OF IGGY VENTURES LLC","slug":"bridge-street-group-llc-on-behalf-of-iggy-ventures-llc","state":"DC","country":"United States of America","description":"Lobbying Firm","totalSpending":0,"filings":10,"yearlySpending":[{"year":2021,"income":0},{"year":2022,"income":0},{"year":2023,"income":0}],"issues":["BAN","FIN","CSP"],"firms":["EXIGENT GOVERNMENT RELATIONS"],"lobbyists":["JONATHAN BERGNER"],"govEntities":["HOUSE OF REPRESENTATIVES","SENATE"],"sampleDescriptions":["Financial Literacy\nConsumer Financial Data Protection","Financial Literacy\nConsumer Financial Data Protection","Financial Literacy\nConsumer Financial Data Protection","Financial Literacy\nFinancial Data Security and Privacy Issues","Financial Literacy\nFinancial Data Security and Privacy Issues"],"years":[2021,2022,2023]}