{"id":159094,"name":"CENTRALIA ELEMENTARY SCHOOL DISTRICT","slug":"centralia-elementary-school-district","state":"CA","country":"United States of America","description":"School District","totalSpending":30000,"filings":4,"yearlySpending":[{"year":2018,"income":30000}],"issues":["BUD","EDU"],"firms":["TOWNSEND PUBLIC AFFAIRS, INC"],"lobbyists":["LAURA KROEGER","A WEBSTER"],"govEntities":["Education, Dept of","HOUSE OF REPRESENTATIVES","SENATE"],"sampleDescriptions":["appropriations","funding","appropriations","funding","appropriations"],"years":[2018]}