{"id":66190,"name":"CITY OF LOMA LINDA","slug":"city-of-loma-linda","state":"CA","country":"United States of America","description":"Municipality","totalSpending":30000,"filings":5,"yearlySpending":[{"year":2025,"income":30000}],"issues":[{"code":"BUD","display":"Budget/Appropriations"}],"firms":["TOWNSEND PUBLIC AFFAIRS, INC"],"lobbyists":["SAMANTHA MACIEL"],"govEntities":["HOUSE OF REPRESENTATIVES","SENATE"],"sampleDescriptions":["Appropriations","Appropriations, community project funding","Appropriations, community project funding","Appropriations, community project funding","Appropriations, community project funding"]}