{"id":193861,"name":"CLEARING HOUSE PAYMENTS COMPANY LLC","slug":"clearing-house-payments-company-llc","state":"DC","country":"United States of America","description":"","totalSpending":340000,"filings":2,"yearlySpending":[{"year":2018,"income":340000}],"issues":["BAN"],"firms":["THE CLEARING HOUSE PAYMENTS COMPANY, LLC"],"lobbyists":["MICHAEL LEE","CARA CAMACHO"],"govEntities":["HOUSE OF REPRESENTATIVES","SENATE"],"sampleDescriptions":["H.R. 1667, \"Financial Institution Bankruptcy Act of 2017\", provisions regarding bankruptcy.\n\nH.R. 10, \"Financial CHOICE Act of 2017\", provisions regarding capital regulation and bankruptcy.\n\nH.R. 4296","H.R. 4296, \"To place requirements on operational risk capital requirements for banking organizations established by an appropriate Federal banking agency\",provisions regarding operational risk.\n\nH.R. "],"years":[2018]}