{"id":55042,"name":"CTIA THE WIRELESS ASSOCATION","slug":"ctia-the-wireless-assocation","state":"DC","country":"United States of America","description":"Wireless Industry Advocacy","totalSpending":680000,"filings":13,"yearlySpending":[{"year":2023,"income":200000},{"year":2024,"income":240000},{"year":2025,"income":240000}],"issues":["TEC","BUD"],"firms":["RESOLUTION PUBLIC AFFAIRS, LLC"],"lobbyists":["LEA SULKALA","HEATHER MCHUGH","ELIZABETH STANLEY","ASHLI SCOTT PALMER","MEGHAN TAIRA"],"govEntities":["HOUSE OF REPRESENTATIVES","SENATE","Office of Management & Budget (OMB)"],"sampleDescriptions":["Issues related to the wireless industry.","HR 1108, to extend FCC auction authority through May 19, 2023 Issues impacting spectrum pipeline development","HR 1108, to extend FCC auction authority through May 19, 2023 Issues impacting spectrum pipeline development","FSGG Appropriations Bill for FY 2024, issues related to continued funding of the Affordable Connectivity Program.","HR 1108, to extend FCC auction authority through May 19, 2023 Issues impacting spectrum pipeline development Impact of no spectrum pipeline on China competition"],"years":[2023,2024,2025]}