{"id":172388,"name":"DELAWARE RIVER WATERFRONT CORPORATION","slug":"delaware-river-waterfront-corporation","state":"PA","country":"United States of America","description":"Design, develop and manage the central Delaware River waterfront","totalSpending":357500,"filings":32,"yearlySpending":[{"year":2018,"income":42000},{"year":2019,"income":42000},{"year":2020,"income":31500},{"year":2021,"income":74000},{"year":2022,"income":42000},{"year":2023,"income":42000},{"year":2024,"income":42000},{"year":2025,"income":42000}],"issues":[{"code":"TRA","display":"Transportation"}],"firms":["BORSKI ASSOCIATES"],"lobbyists":["JOHN TRUMBORE"],"govEntities":["HOUSE OF REPRESENTATIVES","SENATE"],"sampleDescriptions":["Resiliency proposals in potential infrastructure bill\nWetlands credits banking and policies","Status of House infrastructure bill and resiliency standards"]}