{"id":212852,"name":"GUARDING AGAINST PANDEMICS, INC.","slug":"guarding-against-pandemics-inc","state":"DE","country":"United States of America","description":"","totalSpending":2050000,"filings":15,"yearlySpending":[{"year":2021,"income":550000},{"year":2022,"income":1500000}],"issues":[{"code":"HCR","display":"Health Issues"},{"code":"DIS","display":"Disaster Planning/Emergencies"},{"code":"BUD","display":"Budget/Appropriations"},{"code":"MED","display":"Medical/Disease Research/Clinical Labs"},{"code":"SCI","display":"Science/Technology"}],"firms":["GUARDING AGAINST PANDEMICS, INC."],"lobbyists":["VENKATASATYA KROVI","DANIEL ARELLANO"],"govEntities":["HOUSE OF REPRESENTATIVES","SENATE","White House Office"],"sampleDescriptions":["Pandemic preparedness; public healthcare policy and health issues; disaster and emergency planning.","Pandemic preparedness; public healthcare policy and health issues; disaster and emergency planning.","Pandemic preparedness; public healthcare policy and health issues; disaster and emergency planning.","Pandemic preparedness; public healthcare policy and health issues; disaster and emergency planning.","Pandemic preparedness; public healthcare policy and health issues; disaster and emergency planning."]}