{"id":55075,"name":"HEALTH GORILLA","slug":"health-gorilla","state":"CA","country":"United States of America","description":"health care data, interoperability platform","totalSpending":170000,"filings":5,"yearlySpending":[{"year":2023,"income":170000}],"issues":[{"code":"BUD","display":"Budget/Appropriations"},{"code":"HCR","display":"Health Issues"},{"code":"MMM","display":"Medicare/Medicaid"}],"firms":["TARPLIN, DOWNS & YOUNG, LLC"],"lobbyists":["ELIZABETH MURRAY","CHARLOTTE IVANCIC","EMILY MURRY","KIMBERLY BRANDT","RAISSA DOWNS","LAURA FRIEDEL","MARGARET JOSEPH","JENNIFER YOUNG","PAMELA SMITH","PETER FISE"],"govEntities":["Health & Human Services, Dept of (HHS)","HOUSE OF REPRESENTATIVES","SENATE"],"sampleDescriptions":["health information technology","health information technology","health information technology","Implementation of qualified health information networks","Implementation of qualified health information networks"]}