{"id":208251,"name":"HUNTSMAN INTERNATIONAL LLC","slug":"huntsman-international-llc","state":"TX","country":"United States of America","description":"&#226;€‹Technology development and manufacturing","totalSpending":90000,"filings":4,"yearlySpending":[{"year":2021,"income":90000}],"issues":["TRD"],"firms":["BANNER PUBLIC AFFAIRS, LLC"],"lobbyists":["RICHARD HOAR","CHRISTIAN WHITON"],"govEntities":["HOUSE OF REPRESENTATIVES","SENATE"],"sampleDescriptions":["trade policy","trade policy, P.L. 116-260, Consolidated Appropriations Act, 2021, FY 2022 Defense Appropriations.","trade policy, P.L. 116-260, Consolidated Appropriations Act, 2021, FY 2022 Defense Appropriations.","trade policy, P.L. 116-260, Consolidated Appropriations Act, 2021, H.R. 4432, Department of Defense Appropriations Act, 2022."],"years":[2021]}