{"id":112311,"name":"LOVELACE BIOMEDICAL RESEARCH INSTITUTE","slug":"lovelace-biomedical-research-institute","state":"NM","country":"United States of America","description":"Respiratory disease reaserch","totalSpending":680000,"filings":32,"yearlySpending":[{"year":2018,"income":180000},{"year":2019,"income":20000},{"year":2020,"income":80000},{"year":2021,"income":80000},{"year":2022,"income":80000},{"year":2023,"income":80000},{"year":2024,"income":80000},{"year":2025,"income":80000}],"issues":[{"code":"DEF","display":"Defense"},{"code":"BUD","display":"Budget/Appropriations"},{"code":"ANI","display":"Animals"},{"code":"ENV","display":"Environment/Superfund"}],"firms":["CASSIDY & ASSOCIATES, INC."],"lobbyists":["MICHELLE GREENE","KAI ANDERSON","AMELIA JENKINS","DONNA DENISON","KELLEY HUDAK"],"govEntities":["Agriculture, Dept of (USDA)","Defense, Dept of (DOD)","Energy, Dept of","HOUSE OF REPRESENTATIVES","SENATE","White House Office"],"sampleDescriptions":["Medical Research","General Congressional Updates; federal contracting support, radioactive waste resolution","Animal Welfare Act-animal welfare issues; no specific legislation; monitoring","Animal Welfare Act-animal welfare issues; no specific legislation; monitoring","General Congressional Updates; federal contracting support, radioactive waste resolution"]}