{"id":54525,"name":"NAUTICUS ROBOTICS HOLDINGS, INC. D/B/A NAUTICUS ROBOTICS","slug":"nauticus-robotics-holdings-inc-dba-nauticus-robotics","state":"TX","country":"United States of America","description":"Marine robotics","totalSpending":50000,"filings":3,"yearlySpending":[{"year":2023,"income":50000}],"issues":[{"code":"BUD","display":"Budget/Appropriations"}],"firms":["K&L GATES, LLP"],"lobbyists":["PAUL STIMERS","SARAH SWANSON","ANDREW TABLER","SEAN MCGLYNN","MATTHEW MANNING","DARRELL CONNER"],"govEntities":["HOUSE OF REPRESENTATIVES","SENATE"],"sampleDescriptions":["FY 2024 Defense Appropriations funding for Unmanned Underwater Vehicle (UUV) activities.","FY2024 National Defense Appropriations Act (Unnumbered bill); appropriations funding for Unmanned Underwater Vehicle (UUV) activities.","FY2024 National Defense Appropriations Act (Unnumbered bill); appropriations funding for Unmanned Underwater Vehicle (UUV) activities."]}