{"id":51432,"name":"NEW CENTURY PARTNERSHIP O/B/O MORSELIFE HEALTH SYSTEMS","slug":"new-century-partnership-obo-morselife-health-systems","state":"FL","country":"United States of America","description":"Business development firm","totalSpending":150000,"filings":16,"yearlySpending":[{"year":2022,"income":30000},{"year":2023,"income":40000},{"year":2024,"income":40000},{"year":2025,"income":40000}],"issues":["HCR","BUD","EDU"],"firms":["NEW CENTURY GOVERNMENT AFFAIRS (F/K/A TERRENCE C. WOLFE)"],"lobbyists":["TERRENCE WOLFE"],"govEntities":["HOUSE OF REPRESENTATIVES","SENATE"],"sampleDescriptions":["Appropriations","Appropriations","Holocaust Education.","Community Funding Project for healthcare workforce.","Holocaust Education."],"years":[2022,2023,2024,2025]}