{"id":58989,"name":"PORT OF CASCADE LOCKS","slug":"port-of-cascade-locks","state":"OR","country":"United States of America","description":"Public port. Economic development activities, owner of the Bridge of the Gods","totalSpending":126000,"filings":10,"yearlySpending":[{"year":2024,"income":96000},{"year":2025,"income":30000}],"issues":[{"code":"ECN","display":"Economics/Economic Development"},{"code":"TRA","display":"Transportation"},{"code":"MAR","display":"Marine/Maritime/Boating/Fisheries"}],"firms":["MAHR STRATEGIES"],"lobbyists":["DANIEL MAHR"],"govEntities":["Environmental Protection Agency (EPA)","HOUSE OF REPRESENTATIVES","Maritime Administration (MARAD)","SENATE"],"sampleDescriptions":["Business development loans Transportation funding Other economic development activities","Business development loans Transportation funding Other economic development activities","Port grants","funding","Grant opportunities"]}