{"id":122958,"name":"SAN PASQUAL BAND OF MISSION INDIANS","slug":"san-pasqual-band-of-mission-indians","state":"CA","country":"United States of America","description":"","totalSpending":0,"filings":33,"yearlySpending":[{"year":2018,"income":0},{"year":2019,"income":0},{"year":2020,"income":0},{"year":2021,"income":0},{"year":2022,"income":0},{"year":2023,"income":0},{"year":2024,"income":0},{"year":2025,"income":0}],"issues":[{"code":"IND","display":"Indian/Native American Affairs"}],"firms":["HALL ESTILL HARDWICK GABLE GOLDEN & NELSON"],"lobbyists":["JOSEPH MEMBRINO"],"govEntities":["Bureau of Indian Affairs (BIA)","Interior, Dept of (DOI)"],"sampleDescriptions":["San Luis Rey (CA) Indian water rights settlement","San Luis Rey (CA) Indian water rights settlement","San Luis Rey (CA) Indian water rights settlement","San Luis Rey (CA) Indian water rights settlement","water rights settlement"]}