{"id":64619,"name":"SEALED INC.","slug":"sealed-inc","state":"NY","country":"United States of America","description":"climate technology","totalSpending":70000,"filings":4,"yearlySpending":[{"year":2025,"income":70000}],"issues":[{"code":"ENG","display":"Energy/Nuclear"},{"code":"TAX","display":"Taxation/Internal Revenue Code"}],"firms":["MERCURY PUBLIC AFFAIRS, LLC"],"lobbyists":["JAMES MESSNER","ANNE EMERSON"],"govEntities":["Energy, Dept of","Environmental Protection Agency (EPA)","HOUSE OF REPRESENTATIVES","SENATE","White House Office"],"sampleDescriptions":["issues related to preserve and deregulate IRA Rebates","issues related to preserve and deregulate IRA Rebates","issues related to preserve and deregulate IRA Rebates","issues related to preserve and deregulate IRA Rebates","issues related to preserve and deregulate IRA Rebates"]}