{"id":202005,"name":"SMALL BUSINESS IN TRANSPORTATION COALITION","slug":"small-business-in-transportation-coalition","state":"DC","country":"United States of America","description":"501 (c)(6) organization representing small businesses in the trucking industry","totalSpending":0,"filings":46,"yearlySpending":[{"year":2018,"income":0},{"year":2019,"income":0},{"year":2020,"income":0},{"year":2021,"income":0},{"year":2022,"income":0},{"year":2023,"income":0},{"year":2024,"income":0},{"year":2025,"income":0}],"issues":["TRU","SMB","TRA"],"firms":["THE SOCCI LAW FIRM, PLLC (FKA INFLUENCE STRATEGIES)"],"lobbyists":["LAURENCE SOCCI"],"govEntities":["Federal Motor Carrier Safety Administration","HOUSE OF REPRESENTATIVES","SENATE","Transportation, Dept of (DOT)"],"sampleDescriptions":["All issues relating to the trucking, small business and transportation industries.","All issues relating to the trucking, small business and transportation industries.","All issues relating to the trucking, small business and transportation industries.","All issues and legislation relating to the trucking industry, including the electronic logging device mandate, hours of service issues, safe truck parking issues, issues involving the Department of Tr","All legislation and regulations relating tot he trucking industry, including the Electronic Logging Device Mandate, Hours of Service regulations, Safe Truck Parking, and FMCSA rules and regulations"],"years":[2018,2019,2020,2021,2022,2023,2024,2025]}