{"id":206204,"name":"STUDENTS FOR LIFE ACTION","slug":"students-for-life-action","state":"VA","country":"United States of America","description":"","totalSpending":0,"filings":27,"yearlySpending":[{"year":2020,"income":0},{"year":2021,"income":0},{"year":2022,"income":0},{"year":2023,"income":0},{"year":2024,"income":0},{"year":2025,"income":0}],"issues":["FAM","GOV"],"firms":["STUDENTS FOR LIFE ACTION"],"lobbyists":["RACHEL SUMMA","BROOKE PAZ","SAVANNA DERETICH"],"govEntities":["Executive Office of the President (EOP)","Food & Drug Administration (FDA)","Health & Human Services, Dept of (HHS)","HOUSE OF REPRESENTATIVES","President of the U.S.","SENATE","Natl Institutes of Health (NIH)","Smithsonian Institution","U.S. Agency for International Development (USAID)","Justice, Dept of (DOJ)","Centers For Disease Control & Prevention (CDC)","Defense, Dept of (DOD)","Environmental Protection Agency (EPA)","Administration for Children & Families (ACF)","Agriculture, Dept of (USDA)","Equal Employment Opportunity Commission (EEOC)","Federal Bureau of Investigation (FBI)","Veterans Affairs, Dept of (VA)","Occupational Safety & Health Administration (OSHA)"],"sampleDescriptions":["Abortion, Paid Family Leave, Adoption, Foster Care, Euthanasia and Physician Assisted Suicide","Abortion, Paid Family Leave, Adoption, Foster Care, Euthanasia and Physician Assisted Suicide","S.78 - SAVE Moms and Babies Act of 2021\nH.R.1 - For the People Act of 2021\nH.R.5 - Equality Act\nH.J.Res.17 - Removing the deadline for the ratification of the equal rights amendment.\nH.R.51 - Washingt","Abortion/adoption/foster care","S.78 - SAVE Moms and Babies Act of 2021\nH.R.1 & S.1 - For the People Act of 2021\nH.R.5 & S. 393- Equality Act\nH.R. 51 & S. 51 - Washington, D.C. Admission Act\nH.R. 2782 - Womans Right To Know Act\nH.R."],"years":[2020,2021,2022,2023,2024,2025]}