{"id":200729,"name":"THE CORMAC GROUP, LLC ON BEHALF OF BANK MOBILE, INC.","slug":"the-cormac-group-llc-on-behalf-of-bank-mobile-inc","state":"DC","country":"United States of America","description":"Lobbying and Consulting Firm","totalSpending":0,"filings":6,"yearlySpending":[{"year":2019,"income":0},{"year":2020,"income":0}],"issues":["EDU"],"firms":["NEW CENTURY GOVERNMENT AFFAIRS (F/K/A TERRENCE C. WOLFE)"],"lobbyists":["TERRENCE WOLFE"],"govEntities":["HOUSE OF REPRESENTATIVES","SENATE"],"sampleDescriptions":["Student refund disbursement","Student refund disbursement","Student refund disbursement","Student refund disbursement","Student refund disbursement"],"years":[2019,2020]}