{"id":67936,"name":"TRAFIGURA PTE LTD","slug":"trafigura-pte-ltd","state":"TX","country":"United States of America","description":"Energy Development","totalSpending":160000,"filings":3,"yearlySpending":[{"year":2025,"income":160000}],"issues":["ENG"],"firms":["RAGNAR GROUP LLC"],"lobbyists":["MICHAEL ANDREWS","ROBERT WASINGER"],"govEntities":["Energy, Dept of","HOUSE OF REPRESENTATIVES","SENATE","State, Dept of (DOS)"],"sampleDescriptions":["Sustainable energy projects","Energy issues","Energy issues"],"years":[2025]}