{"id":205434,"name":"U.S. ACRES COALITION","slug":"us-acres-coalition","state":"AZ","country":"United States of America","description":"U.S. ACRES Coalition is a 501(c)(3) advocacy coalition.","totalSpending":0,"filings":2,"yearlySpending":[{"year":2020,"income":0}],"issues":["AGR","TEC"],"firms":["ALPHA STRATEGIES, LLC"],"lobbyists":["ADNAN JALIL"],"govEntities":["Agriculture, Dept of (USDA)","HOUSE OF REPRESENTATIVES","SENATE","U.S. Agency for International Development (USAID)"],"sampleDescriptions":["Rural broadband infrastructure.","Rural broadband infrastructure.","Rural Broadband"],"years":[2020]}