{"id":204083,"name":"VOLVO GROUP NORTH AMERICA LLC","slug":"volvo-group-north-america-llc","state":"DC","country":"United States of America","description":"Manufacturer of trucks, buses, construction equipment and marine and industrial engines","totalSpending":30000,"filings":6,"yearlySpending":[{"year":2020,"income":30000}],"issues":[{"code":"TRA","display":"Transportation"}],"firms":["COVINGTON & BURLING LLP"],"lobbyists":["PETER LICHTENBAUM","SAMANTHA CLARK"],"govEntities":["HOUSE OF REPRESENTATIVES","SENATE","Transportation, Dept of (DOT)"],"sampleDescriptions":["Section 7613 of the Fiscal Year 2020 National Defense Authorization Act","Section 7613 of the Fiscal Year 2020 National Defense Authorization Act","Section 7613 of the Fiscal Year 2020 National Defense Authorization Act","Section 7613 of the Fiscal Year 2020 National Defense Authorization Act","Section 7613 of the Fiscal Year 2020 National Defense Authorization Act"]}