{"id":121953,"name":"WESTAR ENERGY","slug":"westar-energy","state":"KS","country":"United States of America","description":"","totalSpending":0,"filings":5,"yearlySpending":[{"year":2018,"income":0},{"year":2019,"income":0}],"issues":["ENG","HOM"],"firms":["GOVERNMENTAL STRATEGIES, INC."],"lobbyists":["TIMOTHY SMITH"],"govEntities":["HOUSE OF REPRESENTATIVES","SENATE"],"sampleDescriptions":["S. 1460, Energy and Natural Resources Act","S. 79, Securing Energy Infrastructure Act\n\nH.R. 3050, Enhancing State Energy Security Planning and Emergency Preparedness Act of 2017\n\nHR 5239, Cyber Sense Act of 2018\n\nHR 5240, Enhancing Grid Securit","S. 1460, Energy and Natural Resources Act","S. 79, Securing Energy Infrastructure Act\nS. 2392, Cyber Support for Anti-Terrorism by Fostering Effective Technologies Act of 2018\nS. 2836, Preventing Emerging Threats Act of 2018\nH.R. 3050, Enhancin","S. 1460, Energy and Natural Resources Act"],"years":[2018,2019]}