{"id":213782,"name":"ZING HEALTH HOLDINGS, INC.","slug":"zing-health-holdings-inc","state":"IL","country":"United States of America","description":"Provider of Medicare Advantage Plans","totalSpending":600000,"filings":17,"yearlySpending":[{"year":2022,"income":120000},{"year":2023,"income":160000},{"year":2024,"income":160000},{"year":2025,"income":160000}],"issues":["MMM"],"firms":["MEHLMAN CONSULTING, INC."],"lobbyists":["STEVE HARO","DEAN ROSEN","DAVID THOMAS","ELISE FINLEY PICKERING","BRUCE MEHLMAN","SAGE EASTMAN","LAUREN ARONSON","MICHAEL ROBINSON","CONSTANTINE HINGSON","HELEN TOLAR","NICHOLE DISTEFANO","MCKENZIE BRICE","PAUL THORNELL","ALEXANDER PERKINS","ROSEMARY GUTIERREZ","STEPHEN COTE","VICTORIA FLOOD","ZACHARY MALLOVE","CAITLIN VAN SANT","LISA GOLDMAN","ALYENE MLINAR","ERICA CHABOT","ANNIE WOLF","NAVEEN PARMAR","JON ADAME","JOSEPH BROWN","EARL FLOOD"],"govEntities":["HOUSE OF REPRESENTATIVES","SENATE","Centers For Medicare and Medicaid Services (CMS)"],"sampleDescriptions":["Issues related to Medicare Advantage Plans","Issues related to Medicare Advantage Plans","Issues related to Medicare Advantage Plans","Issues related to Medicare Advantage Plans. Issues related to health equity, diabetes care, mental health, and Medicare Advantage Star Ratings.","Issues related to Medicare Advantage Plans. Issues related to health equity, diabetes care, mental health, and Medicare Advantage Star Ratings."],"years":[2022,2023,2024,2025]}