{"id":401105040,"name":"A10 ASSOCIATES, LLC","slug":"a10-associates-llc","totalIncome":19611666.33,"filings":413,"yearlyIncome":[{"year":2019,"income":1540000},{"year":2020,"income":2940000},{"year":2021,"income":2140000},{"year":2022,"income":2200000},{"year":2024,"income":5055000},{"year":2025,"income":5736666.33}],"clients":["ASCENSUS","DREW COMPANY","J. DERENZO COMPANIES","MYOMO, INC.","QUANTUM COMPUTING, INC.","VINEYARD WIND, LLC","CDR MAGUIRE INC.","A-TO-BE USA LLC","CORMO USA INC.","THE LIGHT FOUNDATION","LUPOLI COMPANIES","GOLDBERG SEGALLA ON BEHALF OF PARKERVISION","PWC, INC.","GREYSCAN AUSTRALIA PTY LTD.","MOBILE MEDICAL INTERNATIONAL CORPORATION (MMIC)","AERIS ENVIRONMENTAL LTD","KAREN BACARDI","ONECHIROPRACTIC","TRANSTAR AUTOBODY TECHNOLOGIES, LLC","MEDALLIA, INC.","POWERHOUSE CAPITAL, LLC","THE FALLON COMPANY","BLINK CHARGING CO.","SHAWMUT CORPORATION","GRUPO ECOTEK","MUFON","SHARC ENERGY SYSTEMS","REROUTE AMERICAS","SALISBURY BEACH PARTNERSHIP","SPRINKLR","INTERSTATE BUSINESS SOLUTIONS","EDGEENERGY","CAMBRIDGE COLLEGE","SMARTCTY","LOUNGE LIZARD WORLDWIDE INC.","MONETTE FARM","FLAMINGO AIR, INC.","DREAM CENTER INDIANAPOLIS","CLEANLIGHT","CARBON RIVERS, INC.","SOLARTECH ENERGY SYSTEMS, INC.","WATERKEEPER ALLIANCE","RIVERGREEN LLC","GALACTIC LITIGATION PARTNERS, LLC","MGM TRANSFORMER COMPANY","ALLIED POWER AND CONTROL","NEW CITY DEVELOPMENT PARTNERS","INTELLECTUAL TECHNOLOGY, INC.","RMS ENERGY CO. LLC","AESTHETIC MEDICAL PROVIDERS OF NEW HAMPSHIRE","ORIGIN PROPERTY GROUP","HAYNES GROUP INC.","WNDR GLOBAL, INC.","VEHYA","STATES MANUFACTURING CORPORATION","COMMUNITY FIRM (DBA COMMUNITY ECONOMIC DEFENSE PROJECT","NEOVOLTA INC.","INDIGOV CORPORATION","FASTGRID LLC","AMERICUS ENERGY LLC","SIDEWINDER ENTERPRISES LLC","LEMMA HOLDINGS INC.","KNOBELSDORFF ENTERPRISES, INC.","CENTER PHASE ENERGY LLC","MOMENTUM CHARTER SOLUTIONS INC.","VERUM INGREDIENTS INC.","BLACK BUFFALO 3D CORPORATION","BLACKTEAL ENERGY","IDEAL OPTION, PLLC","MAXEON AMERICAS, INC.","PANELMATIC ELECTRICAL SOLUTIONS, INC.","KUCOIN","CERTIK","FIRST SOURCE ELECTRONICS LLC","E-FORCE MARINE","HONEYCOMB DIGITAL INVESTMENTS, LLC","EMURGO GROUP PTE. LTD.","ERD METAL INC.","EXPION 360 INC."],"lobbyists":["JESSICA TOCCO","WILLIAM DEVINE","DANNY MCNAMARA","BRIDGID CHANDLER","CHRISTINE CALLAHAN","LINDSAY PLETCH","DEANNA DEVENEY","ALEXANDER FRIES","HALEY WEEKS"],"issues":["FIN","RES","HCR","SCI","ENG","TRA","ENV","CSP","NAT","CPI","MED","BUD","AGR","CPT","GOV","ECN","IMM","DEF","DIS","AER","APP","RET","FOO","AVI","UNM","MMM","MAN","TAX","LAW","HOU","CAW","TAR","MAR"],"clientCount":79,"years":[2019,2020,2021,2022,2024,2025]}