{"id":401107308,"name":"LODESTONE DC","slug":"lodestone-dc","totalIncome":2143000,"filings":74,"yearlyIncome":[{"year":2023,"income":512000},{"year":2024,"income":931000},{"year":2025,"income":700000}],"clients":["BLUE LEARNING","DATA QUALITY CAMPAIGN, INC.","REGIONAL AIRLINE ASSOCIATION","COMMUNITIES IN SCHOOLS","EXCELLENCE IN EDUCATION NATIONAL, INC.","VITALSOURCE TECHNOLOGIES, LLC","BETTER FUTURE FORWARD","AMERICAN INSTITUTES FOR RESEARCH","RED MAPLE CONSULTING, LLC (ON BEHALF OF SKYROCKET EDUCATION SERVICES)"],"lobbyists":["LINDSAY FRYER","JAMES BERGERON"],"issues":[null,"EDU","BUD","AVI","TAX","BNK","CSP","LBR"],"clientCount":9,"years":[2023,2024,2025]}