{"id":138371,"name":"ADAM FISCHER","slug":"adam-fischer","revolvingDoor":true,"governmentPositions":["Professional Staff Member, U.S. House Committee on Energy and Commerce (Majority), 2019-2022"],"totalFilings":141,"yearlyActivity":[{"year":2021,"filings":1,"clients":1,"firms":1,"issues":["ENV"]},{"year":2022,"filings":27,"clients":3,"firms":1,"issues":["BUD","ENG","ENV","TAX"]},{"year":2023,"filings":47,"clients":4,"firms":1,"issues":[]},{"year":2024,"filings":40,"clients":5,"firms":1,"issues":["ENG","ENV","BUD","TAX"]},{"year":2025,"filings":26,"clients":3,"firms":1,"issues":["ENG","ENV","TAX","BUD"]}],"topClients":[{"name":"WINDWARD FUND","filings":48},{"name":"ELECTRIFY AMERICA, LLC","filings":24},{"name":"LEAGUE OF CONSERVATION VOTERS","filings":24},{"name":"NATURAL RESOURCES DEFENSE COUNCIL","filings":19},{"name":"REWIRING AMERICA, INC","filings":12},{"name":"NRDC ACTION FUND, INC.","filings":10},{"name":"SIERRA CLUB","filings":4}],"firms":[{"name":"WAXMAN STRATEGIES","filings":141}],"issues":["ENV","BUD","ENG","TAX"]}