{"id":149053,"name":"ALEX GALLO","slug":"alex-gallo","revolvingDoor":true,"governmentPositions":["Prof. Staff Member, House Armed Services Committee; Intern, Rep. Marge Roukema"],"totalFilings":127,"yearlyActivity":[{"year":2025,"filings":127,"clients":37,"firms":1,"issues":["DEF","ENG","HCR","VET","BUD","EDU","TAX","AVI","SCI","SMB","GOV","FOR","TRA","CPI"]}],"topClients":[{"name":"ADVANCING MENTAL HEALTH FOR MILITARY FAMILIES, LLC","filings":12},{"name":"FUSE ENERGY TECHNOLOGIES CORP.","filings":6},{"name":"QUALTRICS LLC","filings":6},{"name":"STEPHEN SILLER TUNNEL TO TOWERS FOUNDATION","filings":6},{"name":"TYR TACTICAL","filings":4},{"name":"EOS DEFENSE SYSTEMS USA, INC.","filings":4},{"name":"STRIDER TECHNOLOGIES, INC.","filings":4},{"name":"EUTELSAT NETWORK SOLUTIONS (F/K/A EACOWT)","filings":4},{"name":"BLACKSEA TECHNOLOGIES","filings":4},{"name":"ECS","filings":4},{"name":"DECISION LENS INC.","filings":4},{"name":"UIPATH","filings":4},{"name":"AE INDUSTRIAL PARTNERS, LP","filings":4},{"name":"SUSTAINMENT","filings":4},{"name":"AMERESCO, INC.","filings":4},{"name":"NOBLEREACH FOUNDATION","filings":3},{"name":"VITOL INC.","filings":3},{"name":"FIRE SECURITY INC.","filings":3},{"name":"REGENT CRAFT INC.","filings":3},{"name":"AAR GOVERNMENT SERVICES, INC.","filings":3},{"name":"ARMAMENT RESEARCH COMPANY","filings":3},{"name":"YORK SPACE SYSTEMS","filings":3},{"name":"RELATIVITY SPACE","filings":3},{"name":"PRAIRIE BAND LLC","filings":3},{"name":"CONTI FEDERAL SERVICES","filings":3},{"name":"IAG CAPITAL MANAGEMENT, LLC","filings":3},{"name":"UNIVERSITY OF NOTRE DAME","filings":2},{"name":"TIBERIUS AEROSPACE, INC.","filings":2},{"name":"BP AMERICA INC.","filings":2},{"name":"ENSCO","filings":2},{"name":"ORBIT FAB","filings":2},{"name":"NANOGRAF CORPORATION","filings":2},{"name":"DATABRICKS, INC.","filings":2},{"name":"NOVA TECHNOLOGIES","filings":2},{"name":"INVERIS TRAINING SOLUTIONS","filings":2},{"name":"UNIVERSITY OF WISCONSIN-MADISON","filings":1},{"name":"AEGILYS","filings":1}],"firms":[{"name":"BGR GOVERNMENT AFFAIRS","filings":127}],"issues":["DEF","ENG","HCR","VET","BUD","EDU","TAX","AVI","SCI","SMB","GOV","FOR","TRA","CPI"]}