{"id":72793,"name":"CHARLES CARITHERS","slug":"charles-carithers","revolvingDoor":true,"governmentPositions":["Prof Staff, House Homeland (Thompson); Brookings Legis Fellow, Senate Homeland (Carper)","Prof Staff, House Homeland (Thompson); Brookings Legis Fellow,Senate Homeland (Carper)","Prof Staff, House Homeland (Thompson); Brookings Legis Fellow Senate Homeland (Carper)"],"totalFilings":519,"yearlyActivity":[{"year":2020,"filings":59,"clients":10,"firms":1,"issues":["HOM","DEF","BUD","CPI","IMM","SCI","AVI","INT"]},{"year":2021,"filings":108,"clients":15,"firms":1,"issues":["BUD","HOM","HCR","MMM","ENG","MED","CPI","DEF","GOV","BAN","FOR","TRD","TAX","COM","TEC","NAT"]},{"year":2022,"filings":100,"clients":19,"firms":2,"issues":["DEF","EDU","HOM","SCI","HCR","BUD","DIS","TEC","GOV","BAN","FOR","TAX","COM","CPI","IND","FIN","ENG","NAT","VET","TRA"]},{"year":2023,"filings":91,"clients":17,"firms":1,"issues":[]},{"year":2024,"filings":84,"clients":16,"firms":1,"issues":["EDU","DEF","TRA","SCI","HOM","FIN","IND","BUD","COM","AVI","CPT","GOV","CPI","LBR","TAX","CSP","RRR","TRU"]},{"year":2025,"filings":77,"clients":21,"firms":1,"issues":["COM","DEF","EDU","HOM","BUD","GOV","VET","HCR","SCI","TAX","RRR","TRU","TEC","CPI","LBR","AVI","TRD","AER","TRA","FOR","IND","FIN","ENG","ENV"]}],"topClients":[{"name":"NUTANIX, INC. AND ITS AFFILIATES","filings":36},{"name":"TUNICA BILOXI TRIBE OF LOUISIANA","filings":36},{"name":"SHIFT5, INC.","filings":34},{"name":"CACI INTERNATIONAL, INC.","filings":31},{"name":"GIANT OAK, INC.","filings":24},{"name":"ATLANTA UNIVERSITY CENTER CONSORTIUM, INC.","filings":23},{"name":"BOSSIER PARISH POLICE JURY","filings":21},{"name":"QUANTUM TECHNOLOGY SCIENCES, INC.","filings":20},{"name":"IHEARTMEDIA, INC.","filings":20},{"name":"ALABAMA AGRICULTURAL AND MECHANICAL UNIVERSITY","filings":20},{"name":"IRIDIUM SATELLITE LLC","filings":19},{"name":"SYNACK, INC.","filings":18},{"name":"MERLIN INTERNATIONAL, INC.","filings":18},{"name":"HSBC TECHNOLOGY & SERVICES USA INC.","filings":16},{"name":"APPLIED INTUITION, INC.","filings":15},{"name":"GOOGLE CLIENT SERVICES","filings":14},{"name":"UNITED NEGRO COLLEGE FUND, INC.","filings":11},{"name":"ID.ME, LLC","filings":11},{"name":"EVERBRIDGE, INC.","filings":9},{"name":"ASSOCIATED UNIVERSITIES, INC.","filings":8},{"name":"INTEGRATED ENERGY MATERIALS LLC","filings":8},{"name":"FOUNDATION FOR MISSISSIPPI HISTORY","filings":8},{"name":"GARMIN INTERNATIONAL, INC.","filings":7},{"name":"R4 TECHNOLOGIES, INC.","filings":6},{"name":"SCALE AI, INC.","filings":6},{"name":"EPIRUS, INC.","filings":6},{"name":"DILLARD UNIVERSITY","filings":6},{"name":"MORRIS COLLEGE","filings":5},{"name":"AVIATION TRAINING CONSULTING, LLC","filings":4},{"name":"DAEDALUS INSTITUTE","filings":4},{"name":"AMERICAN SOCIETY FOR RADIATION ONCOLOGY","filings":4},{"name":"PARRAID, LLC","filings":4},{"name":"ZERO - THE END OF PROSTATE CANCER","filings":4},{"name":"JOHN BEAN TECHNOLOGIES CORPORATION","filings":4},{"name":"TRUE ANOMALY, INC.","filings":4},{"name":"DIPLOMATIC PERSPECTIVE","filings":4},{"name":"SNOWFLAKE INC.","filings":4},{"name":"ENVISION TECHNOLOGY, LLC","filings":4},{"name":"KIDS IN NEED OF DEFENSE","filings":3},{"name":"AUGUSTA UNIVERSITY RESEARCH INSTITUTE","filings":3},{"name":"NATIONAL ALLIANCE FOR PUBLIC CHARTER SCHOOLS","filings":2},{"name":"SWYFT, INC.","filings":2},{"name":"SIGMA DEFENSE SYSTEMS LLC","filings":2},{"name":"UNITED AIRLINES INC","filings":2},{"name":"SAAB","filings":2},{"name":"THE BOEING COMPANY","filings":2},{"name":"PRESCIENT EDGE","filings":1},{"name":"EXXONMOBIL","filings":1},{"name":"RICE UNIVERSITY","filings":1},{"name":"PALANTIR","filings":1}],"firms":[{"name":"CORNERSTONE GOVERNMENT AFFAIRS, INC.","filings":517},{"name":"KING & SPALDING LLP","filings":2}],"issues":["HOM","DEF","BUD","CPI","IMM","SCI","AVI","INT","HCR","MMM","ENG","MED","GOV","BAN","FOR","TRD","TAX","COM","TEC","NAT","EDU","DIS","IND","FIN","VET","TRA","CPT","LBR","CSP","RRR","TRU","AER","ENV"]}