{"id":61108,"name":"DOUGLAS MAGUIRE","slug":"douglas-maguire","revolvingDoor":true,"governmentPositions":["None"],"totalFilings":437,"yearlyActivity":[{"year":2018,"filings":40,"clients":13,"firms":1,"issues":["CPI","FIN","TAX","VET","LBR","MMM","IMM","PHA","NAT","HCR","TEC","EDU","FOR","GOV"]},{"year":2019,"filings":36,"clients":13,"firms":1,"issues":["LAW","GOV","FIN","NAT","EDU","TAX","TEC","CPI","FOR","TRD","AGR","PHA","MED","HCR","MMM"]},{"year":2020,"filings":48,"clients":16,"firms":1,"issues":["GOV","FOR","AGR","LAW","TRD","TAX","NAT","EDU","TEC","MMM","MED","HCR","PHA","TOR","SCI","CPI","SPO","CPT","IMM"]},{"year":2021,"filings":86,"clients":23,"firms":1,"issues":["AGR","TRD","TEC","TAX","EDU","HCR","FOR","GOV","CPI","NAT","CPT","SPO","IMM","MED","MMM","PHA","TRA","ENG","INS","FIN","MIA","VET","LBR","GAM","BUD","DIS","ACC"]},{"year":2022,"filings":92,"clients":25,"firms":1,"issues":["TOR","EDU","FOR","BUD","TAX","AGR","GOV","TRD","ENG","GAM","HCR","IMM","INS","NAT","TRA","SPO","CPT","LBR","PHA","TEC","FIN","MIA","ACC","DEF","REL","SCI","ENV"]},{"year":2024,"filings":81,"clients":27,"firms":1,"issues":["FIN","TAX","PHA","TRA","SCI","BAN","REL","ENG","TRD","ENV","HCR","FOR","SPO","IMM","ART","CPT","GOV","LBR","EDU","TOU","DEF","AVI","AGR","RES","TEC"]},{"year":2025,"filings":54,"clients":20,"firms":1,"issues":["FOR","FIN","TAX","AVI","RES","GAM","EDU","BAN","REL","HCR","SCI","ENV","TEC","TRA","TOU","DEF","CPT","SPO","IMM","ART","GOV","LBR","AGR","TAR","VET"]}],"topClients":[{"name":"DEL MONTE FRESH PRODUCE COMPANY","filings":35},{"name":"WALGREEN CO.","filings":26},{"name":"KUWAIT & GULF LINK HOLDING","filings":24},{"name":"COLORADO STATE UNIVERSITY","filings":23},{"name":"AMERICAN TOWER CORPORATION","filings":18},{"name":"APOLLO GLOBAL MANAGEMENT","filings":17},{"name":"ZUFFA AND AFFILIATES","filings":16},{"name":"TALOS ENERGY","filings":15},{"name":"DAR AL HANDASAH CONSULTANTS SHAIR & PARTNERS HOLDINGS LTD","filings":14},{"name":"LOS ANGELES ORGANIZING COMMITTEE FOR THE OLYMPIC AND PARALYMPIC GAMES 2028","filings":12},{"name":"KINROSS GOLD CORPORATION","filings":10},{"name":"KIOXIA AMERICA, INC.","filings":10},{"name":"THE JEWISH FEDERATIONS OF NORTH AMERICA","filings":10},{"name":"UNIVERSITY OF THE PACIFIC","filings":10},{"name":"MODERNA US INC.","filings":9},{"name":"SYNACK, INC.","filings":8},{"name":"CROWELL & MORING LLP OBO VICTIMS OF STATE SPONSORED TERRORISM","filings":8},{"name":"ATLAS AIR, LNC.","filings":8},{"name":"CROWELL & MORING LLP OBO COGITATIVO, INC.","filings":7},{"name":"GLOBAL BANANA SUSTAINABILITY ALLIANCE","filings":7},{"name":"MCDONALD'S CORPORATION","filings":7},{"name":"WALKER & DUNLOP, INC.","filings":7},{"name":"J&F INVESTIMENTOS S.A.","filings":6},{"name":"SALESFORCE.COM INC.","filings":6},{"name":"THE DOE RUN RESOURCES CORPORATION","filings":6},{"name":"SL GREEN REALTY CORP.","filings":6},{"name":"PFH S.P.A.","filings":6},{"name":"TAHOE RESOURCES, INC. (CANADIAN PUBLIC COMPANY)","filings":5},{"name":"PORT LINK GP, LTD. (ON BEHALF OF THE PORT FUND L.P.)","filings":5},{"name":"KGL INVESTMENT COMPANY, KSCC","filings":5},{"name":"CLEAN FUELS ALLIANCE AMERICA","filings":5},{"name":"MGM PUBLIC POLICY, LLC","filings":5},{"name":"CROWELL & MORING OBO ECOLOG INTERNATIONAL","filings":5},{"name":"ACUITY INTERNATIONAL","filings":5},{"name":"OVACURE","filings":4},{"name":"CONSERVATION INTERNATIONAL FOUNDATION","filings":4},{"name":"BLOOM ENERGY","filings":4},{"name":"CAESARS ENTERPRISE SERVICES, LLC","filings":4},{"name":"TOAST, INC.","filings":4},{"name":"OS DISTILLING COMPANY","filings":3},{"name":"TOP RANK, INC.","filings":3},{"name":"NOVARTIS","filings":3},{"name":"C5 CAPITAL","filings":3},{"name":"THE SCOTTS MIRACLE-GRO COMPANY","filings":3},{"name":"KRAFT HEINZ FOODS COMPANY","filings":3},{"name":"PARSONS CORPORATION","filings":3},{"name":"S&P GLOBAL (F/K/A MCGRAW HILL FINANCIAL)","filings":2},{"name":"VERDANT HOLDINGS LLC","filings":2},{"name":"VIRTUSTREAM, INC.","filings":2},{"name":"MARRIOTT INTERNATIONAL, INC.","filings":2}],"firms":[{"name":"BROWNSTEIN HYATT FARBER SCHRECK, LLP","filings":437}],"issues":["CPI","FIN","TAX","VET","LBR","MMM","IMM","PHA","NAT","HCR","TEC","EDU","FOR","GOV","LAW","TRD","AGR","MED","TOR","SCI","SPO","CPT","TRA","ENG","INS","MIA","GAM","BUD","DIS","ACC","DEF","REL","ENV","BAN","ART","TOU","AVI","RES","TAR"]}