{"id":48335,"name":"JENNIFER CERVANTES","slug":"jennifer-cervantes","revolvingDoor":true,"governmentPositions":["U. S. Department of Agriculture, Deputy Chief of Staff for the Secretary of Agriculture","U.S. Department of Agriculture, Deputy Chief of Staff for the Secretary of Agriculture"],"totalFilings":72,"yearlyActivity":[{"year":2018,"filings":12,"clients":3,"firms":1,"issues":["AGR"]},{"year":2019,"filings":6,"clients":3,"firms":1,"issues":["AGR"]},{"year":2020,"filings":12,"clients":3,"firms":1,"issues":["AGR"]},{"year":2021,"filings":9,"clients":3,"firms":1,"issues":["AGR"]},{"year":2022,"filings":12,"clients":3,"firms":1,"issues":["AGR"]},{"year":2024,"filings":9,"clients":3,"firms":1,"issues":["AGR"]},{"year":2025,"filings":12,"clients":3,"firms":1,"issues":["AGR"]}],"topClients":[{"name":"FLORIDA SUGAR CANE LEAGUE","filings":24},{"name":"RIO GRANDE VALLEY SUGAR GROWERS","filings":24},{"name":"SUGAR CANE GROWERS COOPERATIVE OF FLORIDA","filings":24}],"firms":[{"name":"FLORIDA SUGAR CANE LEAGUE","filings":72}],"issues":["AGR"]}