{"name":"KATIE PHILLIPS","slug":"katie-phillips","positions":[],"firms":["FEDERAL HALL POLICY ADVISORS, LLC"],"clients":["FERMAT CAPITAL MANAGEMENT","MARSH & MCLENNAN COMPANIES, INC.","NATIONAL ASSOCIATION OF MUTUAL INSURANCE COMPANIES","DEFI EDUCATION FUND","GLOBAL TRADING SYSTEMS, LLC","FIR TREE PARTNERS","ICEYE","MONARCH ALTERNATIVE CAPITAL LP","VANTAGESCORE SOLUTIONS, LLC","ALLSTATE INSURANCE COMPANY","BANCO AZTECA, SA","BIPARTISAN POLICY CENTER ACTION","ARNALL GOLDEN GREGORY (O/B/O HOUSING AUTHORITY OF THE COUNTY OF SANTA BARBARA)","ARNALL GOLDEN GREGORY (O/B/O HOUSING AUTHORITY OF THE COUNTY OF BUTTE)","NATIONAL RENTAL HOME COUNCIL","U.S. MORTGAGE INSURERS","ELECTRONX","NATIXIS INVESTMENT MANAGERS, LLC","PRETIUM"],"filings":228,"issues":[]}