{"id":70409,"name":"LAUREN RUBIN","slug":"lauren-rubin","revolvingDoor":true,"governmentPositions":["Legislative Director - Rep. Suzan DelBene - 2015-2018","Legislative Director - Rep. Suzan DelBene - 2015-18","Legislative Director - Rep. Suzan DelBene 2015-18","Leg. Director - Rep. Suzan DelBene 2015-18","Leg. Director - Rep. Suzan DelBene - 2015-18","Legislative Director, Rep. Suzan DelBene - 2015-18","Legislative Director - Rep. Suzan DelBene, 2015-18","Legislative Director, Rep. Suzan DelBene, 2015-18"],"totalFilings":110,"yearlyActivity":[{"year":2019,"filings":24,"clients":12,"firms":1,"issues":["TAX","HCR","RET"]},{"year":2020,"filings":25,"clients":13,"firms":1,"issues":["TAX","INS","RET"]},{"year":2021,"filings":18,"clients":10,"firms":1,"issues":["TAX","INS","HCR"]},{"year":2022,"filings":19,"clients":11,"firms":1,"issues":["TAX","RET","FIN","HCR"]},{"year":2024,"filings":24,"clients":11,"firms":1,"issues":["TAX"]}],"topClients":[{"name":"SALTCHUK RESOURCES, INC.","filings":11},{"name":"EXXONMOBIL CORPORATION","filings":8},{"name":"WORKING GROUP ON COMPETITIVE INTERNATIONAL TAXATION (INFORMAL COALITION)","filings":8},{"name":"VALERO ENERGY CORPORATION","filings":7},{"name":"ASSURANT, INC.","filings":6},{"name":"NEXTERA ENERGY, INC.","filings":6},{"name":"NEW YORK LIFE INSURANCE COMPANY","filings":5},{"name":"THERMO FISHER SCIENTIFIC INC","filings":5},{"name":"ANHEUSER-BUSCH COMPANIES","filings":5},{"name":"NATIONAL BIODIESEL BOARD","filings":4},{"name":"SECURITIES INDUSTRY & FINANCIAL MARKETS ASSN.","filings":4},{"name":"BLACKROCK, INC.","filings":4},{"name":"AMERICAN EXPRESS TRAVEL RELATED SERVICES, FORMERLY REPORTED AS AMERICAN EXPRESS","filings":4},{"name":"AMERICAN ACADEMY OF PHYSICIAN ASSOCIATES","filings":3},{"name":"THE MARCUS CORPORATION","filings":3},{"name":"MARSH MCLENNAN","filings":3},{"name":"CITIGROUP WASHINGTON, INC.","filings":3},{"name":"CISCO SYSTEMS, INC.","filings":3},{"name":"DUKE ENERGY BUSINESS SERVICES LLC","filings":3},{"name":"ECOLAB INC.","filings":3},{"name":"BECHTEL GROUP, INC.","filings":2},{"name":"MEDTRONIC INC.","filings":2},{"name":"METLIFE GROUP, INC.","filings":2},{"name":"INSTITUTE OF INTERNATIONAL BANKERS","filings":2},{"name":"SAP AMERICA","filings":2},{"name":"GENERAL ELECTRIC COMPANY","filings":1},{"name":"TESLA INC.","filings":1}],"firms":[{"name":"ERNST & YOUNG LLP (WASHINGTON COUNCIL ERNST & YOUNG)","filings":110}],"issues":["TAX","HCR","RET","INS","FIN"]}