{"id":140597,"name":"MICHAEL DOWNING","slug":"michael-downing","revolvingDoor":true,"governmentPositions":["U.S. Dept of Labor - Deputy Assistant Secretary for Intergovernmental Affairs; Noncareer SES - Chief of Staff (Office of Public Affairs); GS-15 U.S. General Services Administration - Deputy Chief of Staff; Noncareer SES - White House Liaison;","U.S. Dpt of Labor - Deputy Asst Secretary for Intergovernmental Affairs; Noncareer SES - Chief of Staff (Office of Public Affairs); GS-15 U.S. General Services Administration - Deputy Chief of Staff; Noncareer SES - White House Liaison; GS-15"],"totalFilings":62,"yearlyActivity":[{"year":2022,"filings":12,"clients":1,"firms":1,"issues":["ACC","BAN","ENV","CPI"]},{"year":2023,"filings":20,"clients":1,"firms":1,"issues":[]},{"year":2024,"filings":14,"clients":1,"firms":1,"issues":["BAN","CDT","FIN","CSP","SCI"]},{"year":2025,"filings":16,"clients":1,"firms":1,"issues":["CSP","SCI","BAN","CDT","BUD","GOV"]}],"topClients":[{"name":"THE INSTITUTE OF INTERNAL AUDITORS","filings":62}],"firms":[{"name":"THE INSTITUTE OF INTERNAL AUDITORS","filings":62}],"issues":["ACC","BAN","ENV","CPI","CDT","FIN","CSP","SCI","BUD","GOV"]}