{"id":70372,"name":"ROSS ARNETT","slug":"ross-arnett","revolvingDoor":true,"governmentPositions":["Senior Associate","Communications Director","Communications Director.","communications director","Communication Director","Communications Direction","Communications director"],"totalFilings":901,"yearlyActivity":[{"year":2019,"filings":188,"clients":22,"firms":1,"issues":["MAR","ENV","ENG","ECN","IND","NAT","BAN","TRD","TRA","HOM","TAX","HCR","VET","HOU","SCI","IMM","AGR","FIN","ROD","CAW","GAM","RES","BEV","BUD","WEL","LAW","SPO"]},{"year":2020,"filings":297,"clients":24,"firms":1,"issues":["IND","BAN","AGR","IMM","TRA","HCR","SCI","TAX","HOU","VET","SPO","WEL","LAW","GAM","TRD","DIS","BEV","BUD","ENV","ENG","MED","ANI","CAW","ROD","NAT","MAR","HOM","ECN","RES","FIN","CPT"]},{"year":2021,"filings":149,"clients":26,"firms":1,"issues":["TRA","DIS","HCR","IND","NAT","VET","HOU","BAN","TAX","ENV","TRD","HOM","ECN","ENG","RES","AGR","MAR","WEL","MED","CAW","ROD","IMM","GAM"]},{"year":2022,"filings":140,"clients":20,"firms":1,"issues":["ENV","TRA","TAX","HCR","ENG","ECN","RES","BAN","CAW","ROD","AGR","IND","HOU","VET","NAT","WEL","GAM","COM","DIS"]},{"year":2024,"filings":89,"clients":15,"firms":1,"issues":["BAN","ENG","ENV","ECN","RES","TRA","TAX","IND","HOU","DIS","TEC"]},{"year":2025,"filings":38,"clients":12,"firms":1,"issues":["ENG","ENV","RES","BNK","TAR","IND","TAX","GAM","TRA","DIS","GOV"]}],"topClients":[{"name":"CA STATE ASSEMBLY","filings":130},{"name":"INTERNATIONAL FACILITY MANAGEMENT ASSN","filings":93},{"name":"GLASS PACKAGING INSTITUTE (GPI)","filings":63},{"name":"SALT RIVER PIMA MARICOPA INDIAN COMMUNITY","filings":61},{"name":"MORONGO BAND OF MISSION INDIANS","filings":50},{"name":"TULARE COUNTY ASSOCIATION OF GOVERNMENTS","filings":48},{"name":"SANTA YNEZ BAND OF CHUMASH INDIANS","filings":42},{"name":"BISHOP PAIUTE TRIBE","filings":41},{"name":"PASKENTA BAND OF NOMLAKI INDIANS","filings":36},{"name":"SAN FRANCISCO BAR PILOTS ASSN","filings":26},{"name":"COLORADO RIVER INDIAN TRIBES","filings":24},{"name":"INTERNATIONAL ASSOCIATION OF MOVERS - (FORMERLY -H H G F A A)","filings":24},{"name":"COLUSA INDIAN COMMUNITY","filings":24},{"name":"NATIONAL ASSN OF CREDIT MANAGEMENT","filings":23},{"name":"ONEIDA TRIBE OF INDIANS OF WISCONSIN","filings":23},{"name":"CALIFORNIA ASSOCIATION OF VETERAN SERVICE AGENCIES","filings":22},{"name":"FEDERATED INDIANS OF THE GRATON RANCHERIA","filings":22},{"name":"WEST LOS ANGELES VETERANS' COLLECTIVE","filings":18},{"name":"SOCIAL COMPASSION IN LEGISLATION","filings":15},{"name":"KASASA","filings":14},{"name":"NAPA VALLEY VINTNERS ASSOCIATION","filings":14},{"name":"HILLTOP HOLDINGS INC.","filings":13},{"name":"ADVANCED TELESENSORS, INC.","filings":11},{"name":"GLADSTONE INSTITUTE","filings":11},{"name":"INDEPENDENT BANKERS ASSN OF TEXAS","filings":8},{"name":"KARUK TRIBE","filings":8},{"name":"DEKRA NORTH AMERICA","filings":8},{"name":"CALIFORNIA FARM BUREAU FEDERATION","filings":8},{"name":"SAN MANUEL BAND OF MISSION INDIANS","filings":7},{"name":"APPLUS TECHNOLOGIES","filings":6},{"name":"WORLDWIDE ENVIRONMENTAL PRODUCTS (WEP)","filings":4},{"name":"PEACE FOR ANIMALS","filings":3},{"name":"QUAPAW NATION","filings":1}],"firms":[{"name":"PACE, LLP","filings":901}],"issues":["MAR","ENV","ENG","ECN","IND","NAT","BAN","TRD","TRA","HOM","TAX","HCR","VET","HOU","SCI","IMM","AGR","FIN","ROD","CAW","GAM","RES","BEV","BUD","WEL","LAW","SPO","DIS","MED","ANI","CPT","COM","TEC","BNK","TAR","GOV"]}