{"id":69498,"name":"STACEY HUTCHINSON","slug":"stacey-hutchinson","revolvingDoor":true,"governmentPositions":["Deputy Chief of Staff, House of Representatives; Deputy Press Secretary, House of Representatives; Press Secretary, Governor of Virginia","Deputy Chief of Staff, House of Representatives; Deputy Press Secretary, House of Representatives"],"totalFilings":99,"yearlyActivity":[{"year":2018,"filings":8,"clients":1,"firms":1,"issues":["VET","GOV","HOM","DEF","CPI"]},{"year":2019,"filings":27,"clients":2,"firms":1,"issues":["TEC","SCI","LAW","CIV","EDU","HOM","INT","LBR"]},{"year":2020,"filings":32,"clients":4,"firms":1,"issues":["TEC","SCI","LBR","TAX","HCR","FAM","INS","MAN","ENG","ENV","TRD","CPI"]},{"year":2021,"filings":25,"clients":5,"firms":1,"issues":["HOM","SCI","MAN","TRD","ENV","AUT","CPI","TAX","CIV","TEC","ENG","FUE"]},{"year":2022,"filings":7,"clients":4,"firms":1,"issues":["CPI","AUT","SCI","HOM","ENV","MAN","TAX","FUE","TRD"]}],"topClients":[{"name":"ANTI-DEFAMATION LEAGUE","filings":20},{"name":"U.S. CHAMBER OF COMMERCE - CHAMBER TECHNOLOGY ENGAGEMENT CENTER","filings":16},{"name":"MARCH OF DIMES","filings":16},{"name":"XR ASSOCIATION","filings":14},{"name":"BOOZ ALLEN HAMILTON INC.","filings":8},{"name":"SECURITY INDUSTRY ASSOCIATION","filings":8},{"name":"S&P GLOBAL MOBILITY (FORMERLY KNOWN AS IHS MARKIT D/B/A R.L. POLK & CO.)","filings":8},{"name":"ENVIVA LLC (FORMERLY KNOWN AS ENVIVA LP)","filings":7},{"name":"ACCENTURE, LLP","filings":2}],"firms":[{"name":"MONUMENT ADVOCACY","filings":99}],"issues":["VET","GOV","HOM","DEF","CPI","TEC","SCI","LAW","CIV","EDU","INT","LBR","TAX","HCR","FAM","INS","MAN","ENG","ENV","TRD","AUT","FUE"]}