{"name":"THERESA REED","slug":"theresa-reed","positions":["Leg. Director Multiple Members","Leg Director for Multiple Members","Leg. Director for Multiple Members","LD for Multiple Members","LD Multiple Members","LD to Multiple Members","Legislative Director Multiple Members","Leg Director Multiple Members"],"firms":["HANCE SCARBOROUGH"],"clients":["CRIUS TECHNOLOGY GROUP","ALLIANCE FOR PHARMACY COMPOUNDING","THE AMERICAN INSTITUTE OF ARCHITECTS","MJWT CONSULTING ON BEHALF OF WELLMED MEDICAL MANAGEMETN INC.","CREATIVE SOLUTIONS IN HEALTHCARE","HEALTHCARE ALLIANCE FOR PATIENT SAFETY (HCAPS)","DR. JOHN VALENTINI","BUSINESS COUNCIL OF CANADA","THE APP LAB","NATIONAL INDEPENDENT AUTOMOBILE DEALERS ASSOCIATION","BRIAN GLACKIN & ASSOCIATES (ON BEHALF OF CODAN COMMUNICATIONS LLC)"],"filings":194,"issues":[]}