{"id":11000,"name":"THOMAS O'DONNELL","slug":"thomas-o-donnell","revolvingDoor":true,"governmentPositions":["Chief of Staff, House Majority Leader","Chief of Staff, House Majority Leader Dick Gephardt","​​Chief of Staff, House Majority Leader Dick Gephardt","Chief of Staff, House Majority Leader Gephardt","Chief of Staff, House Majority Leader Richard Gephardt"],"totalFilings":232,"yearlyActivity":[{"year":2018,"filings":48,"clients":8,"firms":1,"issues":["LAW","CSP","HCR","MMM","ENG","TRD","DEF","LBR","AGR","AVI","BUD","ENV","TAX"]},{"year":2019,"filings":46,"clients":10,"firms":1,"issues":["BAN","AGR","DEF","BUD","TRD","MMM","TAX","ENG","LBR","LAW","FIN","TRA","ENV","CSP"]},{"year":2020,"filings":78,"clients":11,"firms":1,"issues":["BAN","TRA","TAX","ENV","ENG","FIN","DEF","LBR","CSP","LAW","MMM","BUD","TEC","AVI","HOM","SMB","EDU","FOR"]},{"year":2021,"filings":60,"clients":10,"firms":1,"issues":["TRA","TAX","TEC","ENV","ENG","CSP","LBR","LAW","HOM","EDU","BAN","TRD","FOR","AVI","DEF","UTI","GOV","BUD","FOO","MMM","CIV"]}],"topClients":[{"name":"AMEREN SERVICES COMPANY","filings":36},{"name":"GENERAL ELECTRIC COMPANY (PREVIOUSLY REPORTED AS GE AVIATION)","filings":33},{"name":"GOOGLE CLIENT SERVICES (PREVIOUSLY REPORTED AS GOOGLE)","filings":30},{"name":"THE BOEING COMPANY","filings":30},{"name":"CORECIVIC, INC.","filings":22},{"name":"SCOTTS MIRACLE-GRO COMPANY","filings":20},{"name":"UNITEDHEALTH GROUP, INC.","filings":18},{"name":"THE NEW SCHOOL","filings":9},{"name":"ENTERPRISE HOLDINGS, INC. DBA ENTERPRISE MOBILITY","filings":8},{"name":"INNOVATION REFORM ACTION PROJECT","filings":7},{"name":"HUNTINGTON INGALLS INDUSTRIES","filings":7},{"name":"INTUIT INC.","filings":5},{"name":"BAYER CORPORATION","filings":3},{"name":"LEO HINDERY, JR.","filings":2},{"name":"PRAIRIE STATE GENERATING COMPANY","filings":2}],"firms":[{"name":"GEPHARDT GROUP GOVERNMENT AFFAIRS","filings":232}],"issues":["LAW","CSP","HCR","MMM","ENG","TRD","DEF","LBR","AGR","AVI","BUD","ENV","TAX","BAN","FIN","TRA","TEC","HOM","SMB","EDU","FOR","UTI","GOV","FOO","CIV"]}